omigami/__init__.py
omigami/_version.py
omigami/consensus_model.py
omigami/data_splitter.py
omigami/exceptions.py
omigami/feature_evaluator.py
omigami/feature_selector.py
omigami/permutation_test.py
omigami/plot_utils.py
omigami/post_processor.py
omigami/sync_executor.py
omigami/utils.py
omigami/data_structures/__init__.py
omigami/data_structures/data_models.py
omigami/data_structures/data_types.py
omigami/models/__init__.py
omigami/models/estimator.py
omigami/models/metrics.py
omigami/models/pls.py
omigami/models/sklearn_estimator.py
omigami/models/sklearn_metrics.py
py_muvr/__init__.py
py_muvr/_version.py
py_muvr/consensus_model.py
py_muvr/data_splitter.py
py_muvr/exceptions.py
py_muvr/feature_evaluator.py
py_muvr/feature_selector.py
py_muvr/permutation_test.py
py_muvr/plot_utils.py
py_muvr/post_processor.py
py_muvr/sync_executor.py
py_muvr/utils.py
py_muvr/data_structures/__init__.py
py_muvr/data_structures/data_models.py
py_muvr/data_structures/data_types.py
py_muvr/models/__init__.py
py_muvr/models/estimator.py
py_muvr/models/metrics.py
py_muvr/models/pls.py
py_muvr/models/sklearn_estimator.py
py_muvr/models/sklearn_metrics.py
pymuv/__init__.py
pymuv/_version.py
pymuv/consensus_model.py
pymuv/data_splitter.py
pymuv/exceptions.py
pymuv/feature_evaluator.py
pymuv/feature_selector.py
pymuv/permutation_test.py
pymuv/plot_utils.py
pymuv/post_processor.py
pymuv/sync_executor.py
pymuv/utils.py
pymuv/data_structures/__init__.py
pymuv/data_structures/data_models.py
pymuv/data_structures/data_types.py
pymuv/models/__init__.py
pymuv/models/estimator.py
pymuv/models/metrics.py
pymuv/models/pls.py
pymuv/models/sklearn_estimator.py
pymuv/models/sklearn_metrics.py
pymuvr/__init__.py
pymuvr/_version.py
pymuvr/consensus_model.py
pymuvr/data_splitter.py
pymuvr/exceptions.py
pymuvr/feature_evaluator.py
pymuvr/feature_selector.py
pymuvr/permutation_test.py
pymuvr/plot_utils.py
pymuvr/post_processor.py
pymuvr/sync_executor.py
pymuvr/utils.py
pymuvr/data_structures/__init__.py
py_muvr-1.0.1.dist-info/LICENSE
py_muvr-1.0.1.dist-info/METADATA
py_muvr-1.0.1.dist-info/WHEEL
py_muvr-1.0.1.dist-info/top_level.txt
py_muvr-1.0.1.dist-info/RECORD
